odoo/addons/sale_order_product_assortment/README.rst
odoo/addons/sale_order_product_assortment/__init__.py
odoo/addons/sale_order_product_assortment/__manifest__.py
odoo/addons/sale_order_product_assortment/i18n/ca.po
odoo/addons/sale_order_product_assortment/i18n/es.po
odoo/addons/sale_order_product_assortment/i18n/sale_order_product_assortment.pot
odoo/addons/sale_order_product_assortment/models/__init__.py
odoo/addons/sale_order_product_assortment/models/sale_order.py
odoo/addons/sale_order_product_assortment/models/sale_order_line.py
odoo/addons/sale_order_product_assortment/readme/CONFIGURE.rst
odoo/addons/sale_order_product_assortment/readme/CONTRIBUTORS.rst
odoo/addons/sale_order_product_assortment/readme/DESCRIPTION.rst
odoo/addons/sale_order_product_assortment/readme/ROADMAP.rst
odoo/addons/sale_order_product_assortment/readme/USAGE.rst
odoo/addons/sale_order_product_assortment/static/description/icon.png
odoo/addons/sale_order_product_assortment/static/description/index.html
odoo/addons/sale_order_product_assortment/tests/__init__.py
odoo/addons/sale_order_product_assortment/tests/test_sale_order_product_assortment.py
odoo/addons/sale_order_product_assortment/views/sale_order_view.xml
odoo12_addon_sale_order_product_assortment-12.0.1.0.0.99.dev7.dist-info/METADATA
odoo12_addon_sale_order_product_assortment-12.0.1.0.0.99.dev7.dist-info/WHEEL
odoo12_addon_sale_order_product_assortment-12.0.1.0.0.99.dev7.dist-info/top_level.txt
odoo12_addon_sale_order_product_assortment-12.0.1.0.0.99.dev7.dist-info/RECORD
